src/curieutil.py
src/trie.py
src/trienode.py
curieutil-0.0.5.dist-info/LICENSE.txt
curieutil-0.0.5.dist-info/METADATA
curieutil-0.0.5.dist-info/WHEEL
curieutil-0.0.5.dist-info/top_level.txt
curieutil-0.0.5.dist-info/RECORD
