Metadata-Version: 2.1
Name: curieutil
Version: 0.0.5
Summary: Python Library to translate CURIEs to IRIs and vice versa. Python version based on the Java Implementation: https://github.com/prefixcommons/curie-util and the JavaScript Implementation: https://github.com/geneontology/curie-util-es5
Home-page: https://github.com/geneontology/curie-util-py
Author: Laurent-Philippe Albou
Author-email: laurent.albou@lbl.gov
License: UNKNOWN
Keywords: CURIE,URI,IRI,RDF,OWL
Platform: UNKNOWN
Classifier: Programming Language :: Python :: 3
Classifier: Programming Language :: Python :: 3.6
Classifier: Programming Language :: Python :: 3.7
Requires-Dist: bidict
